setup.py
nogroth/__init__.py
nogroth/admin.py
nogroth/config.py
nogroth/forms.py
nogroth/models.py
nogroth/tests.py
nogroth/management/__init__.py
nogroth/management/commands/__init__.py
nogroth/management/commands/satchmo_nogroth_copy_tiers.py
nogroth/migrations/0001_initial.py
nogroth/migrations/__init__.py
satchmo_nogroth.egg-info/PKG-INFO
satchmo_nogroth.egg-info/SOURCES.txt
satchmo_nogroth.egg-info/dependency_links.txt
satchmo_nogroth.egg-info/top_level.txt