Metadata-Version: 1.0
Name: satchmo-nogroth
Version: 0.1.3
Summary: A tiered weight shipping module for Satchmo that is Administrative Area (i.e. state/province) aware
Home-page: https://github.com/kcharvey/satchmo-nogroth
Author: Kevin Harvey
Author-email: kcharvey@gmail.com
License: BSD
Download-URL: https://github.com/kcharvey/satchmo-nogroth/archive/master.zip
Keywords: django,satchmo,shipping,tiered weight,by state
Platform: Platform independant
Classifier: Development Status :: 5 - Production/Stable
Classifier: Environment :: Other Environment
Classifier: Framework :: Django
Classifier: Intended Audience :: Developers
Classifier: License :: OSI Approved :: BSD License
Classifier: Natural Language :: English
Classifier: Operating System :: OS Independent
Classifier: Programming Language :: Python
Classifier: Topic :: Software Development :: Libraries :: Python Modules
Classifier: Topic :: Internet
